frogtab/__init__.py
frogtab/_cli.py
frogtab/_client.py
frogtab/_env.py
frogtab/_exceptions.py
frogtab/_version.py
frogtab/legacy/frogtab_helpers.py
frogtab/legacy/migrate_config.py
frogtab/local_server/server.py
frogtab/local_server/static/achievements.html
frogtab/local_server/static/demo-week.html
frogtab/local_server/static/demo.html
frogtab/local_server/static/main.js
frogtab/local_server/static/manifest.webmanifest
frogtab/local_server/static/openpgp.min.mjs
frogtab/local_server/static/send.html
frogtab/local_server/static/simple-customizations.css
frogtab/local_server/static/simple.min.css
frogtab/local_server/static/style.css
frogtab/local_server/static/week.html
frogtab/local_server/static/favicons/icon-16-notify.png
frogtab/local_server/static/favicons/icon-16.png
frogtab/local_server/static/favicons/icon-180-apple.png
frogtab/local_server/static/favicons/icon-192.png
frogtab/local_server/static/favicons/icon-32-notify.png
frogtab/local_server/static/favicons/icon-32.png
frogtab/local_server/static/favicons/icon-512.png
frogtab/local_server/templates/help.html
frogtab/local_server/templates/icon-normal.html
frogtab/local_server/templates/icon-notify.html
frogtab/local_server/templates/index.html
frogtab-2.0.4.dist-info/licenses/LICENSE
frogtab-2.0.4.dist-info/licenses/LICENSE_openpgp
frogtab-2.0.4.dist-info/METADATA
frogtab-2.0.4.dist-info/WHEEL
frogtab-2.0.4.dist-info/entry_points.txt
frogtab-2.0.4.dist-info/top_level.txt
frogtab-2.0.4.dist-info/RECORD
