Metadata-Version: 2.4
Name: frogtab
Version: 2.0.4
Summary: Frogtab Local
Author-email: Dave Wilding <tech@dpw.me>
License-Expression: MIT
Project-URL: Documentation, https://github.com/dwilding/frogtab/blob/main/local/README.md#frogtab-local
Project-URL: Source, https://github.com/dwilding/frogtab/tree/main/local
Project-URL: Tracker, https://github.com/dwilding/frogtab/issues
Project-URL: Changelog, https://github.com/dwilding/frogtab/releases
Classifier: Programming Language :: Python :: 3
Classifier: Operating System :: OS Independent
License-File: LICENSE
License-File: LICENSE_openpgp
Requires-Dist: Flask>=2.2.5
Requires-Dist: requests>=2.31.0
Dynamic: license-file
